rctmodelpool/__init__.py
rctmodelpool/demo.py
rctmodelpool/modelpool.py
rctmodelpool/utils/__init__.py
rctmodelpool/utils/lock.py
rctmodelpool/utils/misc.py
rctmodelpool-0.1.9.dist-info/METADATA
rctmodelpool-0.1.9.dist-info/WHEEL
rctmodelpool-0.1.9.dist-info/top_level.txt
rctmodelpool-0.1.9.dist-info/RECORD
